wechat/__init__.py
wechat/base.py
easy_wechat-0.0.1.dist-info/LICENSE
easy_wechat-0.0.1.dist-info/METADATA
easy_wechat-0.0.1.dist-info/WHEEL
easy_wechat-0.0.1.dist-info/top_level.txt
easy_wechat-0.0.1.dist-info/zip-safe
easy_wechat-0.0.1.dist-info/RECORD
